Metadata-Version: 2.1
Name: speach
Version: 0.1a14
Summary: a Python library for managing, annotating, and converting natural language corpuses using popular formats (CoNLL, ELAN, Praat, CSV, JSON, SQLite, VTT, Audacity, TTL, TIG, ISF)
Home-page: https://github.com/neocl/speach/
Author: Le Tuan Anh
Author-email: tuananh.ke@gmail.com
License: MIT License
Project-URL: Bug Tracker, https://github.com/neocl/speach/issues
Project-URL: Source Code, https://github.com/neocl/speach/
Keywords: nlp,annotation,text,corpus,linguistics,ELAN,transcription
Platform: any
Classifier: Programming Language :: Python :: 3
Classifier: Programming Language :: Python :: 3.6
Classifier: Programming Language :: Python :: 3.7
Classifier: Programming Language :: Python :: 3.8
Classifier: Programming Language :: Python :: 3.9
Classifier: Development Status :: 3 - Alpha
Classifier: License :: OSI Approved :: MIT License
Classifier: Environment :: Plugins
Classifier: Intended Audience :: Education
Classifier: Intended Audience :: Science/Research
Classifier: Intended Audience :: Information Technology
Classifier: Intended Audience :: Developers
Classifier: Operating System :: OS Independent
Classifier: Topic :: Text Processing
Classifier: Topic :: Text Processing :: Linguistic
Classifier: Topic :: Software Development :: Libraries :: Python Modules
Requires-Python: >=3.6
